stockvip/client.py
stockvip/stock.py
stockvip/__init__.py
stockvip/process_client/login.cpython-39-x86_64-linux-gnu.so
stockvip/config/ensure_logged_in.cpython-39-x86_64-linux-gnu.so
stockvip/config/config.cpython-39-x86_64-linux-gnu.so
stockvip/process_stock/propTrading.cpython-39-x86_64-linux-gnu.so
stockvip/process_stock/foreign.cpython-39-x86_64-linux-gnu.so
stockvip/process_stock/dividend.cpython-39-x86_64-linux-gnu.so
stockvip/process_stock/supplyAndDemand.cpython-39-x86_64-linux-gnu.so
stockvip/process_stock/ohlcv.cpython-39-x86_64-linux-gnu.so
stockvip-2.0.6.dist-info/top_level.txt
stockvip-2.0.6.dist-info/RECORD
stockvip-2.0.6.dist-info/LICENSE.txt
stockvip-2.0.6.dist-info/METADATA
stockvip-2.0.6.dist-info/WHEEL
