Metadata-Version: 2.1
Name: stockvip
Version: 2.0.6
Summary: Dữ liệu thị trường chứng khoán Việt Nam
Home-page: https://stockvip.vn
Author: stockvip.vn
Author-email: support@stockvip.vn
Classifier: Programming Language :: Python :: 3
Classifier: License :: OSI Approved :: MIT License
Classifier: Operating System :: OS Independent
Requires-Python: >=3.9
License-File: LICENSE.txt
Requires-Dist: pandas==2.1.2
Requires-Dist: requests
